Metadata-Version: 2.1
Name: site-cloner
Version: 0.0.1
Summary: Clone a website
Home-page: https://github.com/Py-Contributors/site-cloner
Author: Deepak Raj
Author-email: deepak008@live.com
Maintainer: Deepak Raj
Maintainer-email: deepak008@live.com
License: UNKNOWN
Platform: UNKNOWN
Classifier: Programming Language :: Python :: 3
Classifier: License :: OSI Approved :: MIT License
Classifier: Operating System :: OS Independent
Classifier: Topic :: Software Development :: Libraries :: Python Modules
Classifier: Topic :: Utilities
Classifier: Topic :: Internet :: WWW/HTTP
Classifier: Topic :: Internet :: WWW/HTTP :: Indexing/Search
Classifier: Topic :: Internet :: WWW/HTTP :: Site Management
Classifier: Topic :: Internet :: WWW/HTTP :: Dynamic Content
Classifier: Topic :: Internet :: WWW/HTTP :: Dynamic Content :: CGI Tools/Libraries
License-File: LICENSE
